kozmoserver_huggingface/__init__.py
kozmoserver_huggingface/codecs/__init__.py
kozmoserver_huggingface/codecs/base.py
kozmoserver_huggingface/codecs/conversation.py
kozmoserver_huggingface/codecs/image.py
kozmoserver_huggingface/codecs/json.py
kozmoserver_huggingface/codecs/jsonlist.py
kozmoserver_huggingface/codecs/numpylist.py
kozmoserver_huggingface/codecs/raw.py
kozmoserver_huggingface/codecs/utils.py
kozmoserver_huggingface/common.py
kozmoserver_huggingface/errors.py
kozmoserver_huggingface/metadata.py
kozmoserver_huggingface/runtime.py
kozmoserver_huggingface/settings.py
kozmoserver_huggingface/version.py
kozmoserver_huggingface-0.1.0.dev1.dist-info/LICENSE
kozmoserver_huggingface-0.1.0.dev1.dist-info/METADATA
kozmoserver_huggingface-0.1.0.dev1.dist-info/WHEEL
kozmoserver_huggingface-0.1.0.dev1.dist-info/RECORD
